README.md
setup.py
evilunicorn/__init__.py
evilunicorn.egg-info/PKG-INFO
evilunicorn.egg-info/SOURCES.txt
evilunicorn.egg-info/dependency_links.txt
evilunicorn.egg-info/top_level.txt