Metadata-Version: 1.0
Name: evilunicorn
Version: 0.0.1
Summary: Evil Unicorn
Home-page: UNKNOWN
Author: UNKNOWN
Author-email: UNKNOWN
License: UNKNOWN
Platform: UNKNOWN
